ev_audio_streaming_transcription_py/__init__.py
ev_audio_streaming_transcription_py/server.py
ev_audio_streaming_transcription_py-1.0.2.dist-info/LICENSE
ev_audio_streaming_transcription_py-1.0.2.dist-info/METADATA
ev_audio_streaming_transcription_py-1.0.2.dist-info/WHEEL
ev_audio_streaming_transcription_py-1.0.2.dist-info/top_level.txt
ev_audio_streaming_transcription_py-1.0.2.dist-info/RECORD
