Metadata-Version: 2.1
Name: ev-audio-streaming-transcription-py
Version: 1.0.2
Summary: Quick test package for RingCenTral Engage Voice Audio Streaming feature.
Home-page: https://github.com/DaKingKong/ev-audio-streaming-transcription-py
Author: Da Kong
Author-email: da.kong@ringcentral.com
License: MIT
Platform: UNKNOWN
Requires-Python: >=3.0
Requires-Dist: google
Requires-Dist: six
